mcdil/__init__.py
mcdil/cli.py
mcdil/mcdil.lark
mcdil/parse.py
mcdil/components/__init__.py
mcdil/components/base.py
mcdil/components/block.py
mcdil/components/transaction.py
mcdil-0.0.2.dist-info/LICENSE
mcdil-0.0.2.dist-info/METADATA
mcdil-0.0.2.dist-info/WHEEL
mcdil-0.0.2.dist-info/entry_points.txt
mcdil-0.0.2.dist-info/top_level.txt
mcdil-0.0.2.dist-info/RECORD
