Metadata-Version: 2.1
Name: mcdil
Version: 0.0.2
Summary: McDic's Language for Minecraft JE Datapack
Author-email: Minsung Kim <spongbob9876@naver.com>
License: Copyright 2023 McDic
Project-URL: Homepage, https://github.com/McDic/MCDIL
Keywords: minecraft,language,compiler
Classifier: Programming Language :: Python :: 3
Classifier: License :: OSI Approved :: MIT License
Requires-Python: >=3.11
License-File: LICENSE
Requires-Dist: lark
